hedron/__init__.py
hedron/cluster.py
hedron/cluster_functions.py
hedron/maps.py
hedron-0.0.6.dist-info/licenses/LICENSE
hedron-0.0.6.dist-info/METADATA
hedron-0.0.6.dist-info/WHEEL
hedron-0.0.6.dist-info/top_level.txt
hedron-0.0.6.dist-info/RECORD
